atexit_tempfile/__init__.py
atexit_tempfile/atexit_cleanup.py
atexit_tempfile/atexit_mkstemp.py
atexit_tempfile/class_cleanup.py
atexit_tempfile-0.0.4.dist-info/METADATA
atexit_tempfile-0.0.4.dist-info/WHEEL
atexit_tempfile-0.0.4.dist-info/licenses/LICENSE
atexit_tempfile-0.0.4.dist-info/RECORD
